sufam/__init__.py
sufam/__main__.py
sufam/_version.py
sufam/mpileup_parser.py
sufam/mutation.py
sufam/revertant.py
sufam/utils.py
sufam-0.4.2.dist-info/DESCRIPTION.rst
sufam-0.4.2.dist-info/METADATA
sufam-0.4.2.dist-info/RECORD
sufam-0.4.2.dist-info/WHEEL
sufam-0.4.2.dist-info/entry_points.txt
sufam-0.4.2.dist-info/metadata.json
sufam-0.4.2.dist-info/top_level.txt
