Metadata-Version: 2.0
Name: sufam
Version: 0.4.2
Summary: So U Found A Mutation?
Home-page: https://github.com/inodb/sufam
Author: Ino de Bruijn
Author-email: ino@ino.pm
License: MIT
Keywords: Python validation mutation mpileup samtools pileup vcf bam
Platform: UNKNOWN
Classifier: Development Status :: 2 - Pre-Alpha
Classifier: Intended Audience :: Science/Research
Classifier: Natural Language :: English
Classifier: License :: OSI Approved :: MIT License
Classifier: Operating System :: OS Independent
Classifier: Programming Language :: Python
Classifier: Programming Language :: Python :: 2
Classifier: Programming Language :: Python :: 2.6
Classifier: Programming Language :: Python :: 2.7
Classifier: Topic :: Software Development :: Libraries :: Python Modules
Requires-Dist: numpy (>=1.9.2)
Requires-Dist: pandas (>=0.16.1)
